mphtestlib/__init__.py
mphtestlib/factorial/__init__.py
mphtestlib-0.0.1.dist-info/LICENSE
mphtestlib-0.0.1.dist-info/METADATA
mphtestlib-0.0.1.dist-info/WHEEL
mphtestlib-0.0.1.dist-info/top_level.txt
mphtestlib-0.0.1.dist-info/RECORD
